design.sv
module PID_Controller (
    input wire clk,
    input wire reset,
    input wire signed [15:0] setpoint,
    input wire signed [15:0] process_variable,
    output reg signed [15:0] control_output,
    output wire signed [15:0] error,
    output wire signed [15:0] integral,
    output wire signed [15:0] derivative,
    output wire signed [31:0] P_term,
    output wire signed [31:0] I_term,
    output wire signed [31:0] D_term,
    output wire signed [31:0] PID_output
);

    // PID coefficients
    parameter signed [15:0] Kp = 16'h1000; // Proportional gain
    parameter signed [15:0] Ki = 16'h0100; // Integral gain
    parameter signed [15:0] Kd = 16'h0800; // Derivative gain

    // State variables
    reg signed [15:0] integral_reg;
    reg signed [15:0] prev_error;
    reg signed [15:0] error_reg;
    reg signed [31:0] P_term_reg;
    reg signed [31:0] I_term_reg;
    reg signed [15:0] derivative_reg;
    reg signed [31:0] D_term_reg;
    reg signed [31:0] PID_output_reg;

    assign error = error_reg;
    assign integral = integral_reg;
    assign derivative = derivative_reg;
    assign P_term = P_term_reg;
    assign I_term = I_term_reg;
    assign D_term = D_term_reg;
    assign PID_output = PID_output_reg;

    always @(posedge clk or posedge reset) begin
        if (reset) begin
            integral_reg <= 16'd0;
            prev_error <= 16'd0;
            control_output <= 16'd0;
        end else begin
            // Calculate error
            error_reg <= setpoint - process_variable;
            
            // Proportional term
            P_term_reg <= Kp * error_reg;
            
            // Integral term
            integral_reg <= integral_reg + error_reg;
            I_term_reg <= Ki * integral_reg;
            
            // Derivative term
            derivative_reg <= error_reg - prev_error;
            D_term_reg <= Kd * derivative_reg;
            
            // PID output
            PID_output_reg <= P_term_reg + I_term_reg + D_term_reg;
            
            // Update control output
            control_output <= PID_output_reg[15:0];
            
            // Update previous error
            prev_error <= error_reg;
        end
    end
endmodule

testbench.sv
module PID_Controller_tb;

    reg clk;
    reg reset;
    reg signed [15:0] setpoint;
    reg signed [15:0] process_variable;
    wire signed [15:0] control_output;

    // Internal signals for dumping
    wire signed [15:0] error;
    wire signed [15:0] integral;
    wire signed [15:0] derivative;
    wire signed [31:0] P_term;
    wire signed [31:0] I_term;
    wire signed [31:0] D_term;
    wire signed [31:0] PID_output;

    // Instantiate the PID controller
    PID_Controller uut (
        .clk(clk),
        .reset(reset),
        .setpoint(setpoint),
        .process_variable(process_variable),
        .control_output(control_output)
    );

    initial begin
        // Initialize inputs
        clk = 0;
        reset = 1;
        setpoint = 16'd100;
        process_variable = 16'd0;

        // Dump VCD file
        $dumpfile("dump.vcd");
        $dumpvars(0, PID_Controller_tb);

        #5 reset = 0;

        #10 process_variable = 16'd50;
        #10 process_variable = 16'd75;
        #10 process_variable = 16'd100;
        #10 process_variable = 16'd125;
        #10 process_variable = 16'd150;

        #100 $finish;
    end

    always #5 clk = ~clk;

endmodule

dump.vcd
$date
	Sun Jul 28 10:57:23 2024
$end
$version
	Icarus Verilog
$end
$timescale
	1s
$end
$scope module PID_Controller_tb $end
$var wire 16 ! control_output [15:0] $end
$var reg 1 " clk $end
$var reg 16 # process_variable [15:0] $end
$var reg 1 $ reset $end
$var reg 16 % setpoint [15:0] $end
$scope module uut $end
$var wire 32 & D_term [31:0] $end
$var wire 32 ' I_term [31:0] $end
$var wire 32 ( PID_output [31:0] $end
$var wire 32 ) P_term [31:0] $end
$var wire 1 " clk $end
$var wire 16 * derivative [15:0] $end
$var wire 16 + error [15:0] $end
$var wire 16 , integral [15:0] $end
$var wire 16 - process_variable [15:0] $end
$var wire 1 $ reset $end
$var wire 16 . setpoint [15:0] $end
$var parameter 16 / Kd $end
$var parameter 16 0 Ki $end
$var parameter 16 1 Kp $end
$var reg 32 2 D_term_reg [31:0] $end
$var reg 32 3 I_term_reg [31:0] $end
$var reg 32 4 PID_output_reg [31:0] $end
$var reg 32 5 P_term_reg [31:0] $end
$var reg 16 6 control_output [15:0] $end
$var reg 16 7 derivative_reg [15:0] $end
$var reg 16 8 error_reg [15:0] $end
$var reg 16 9 integral_reg [15:0] $end
$var reg 16 : prev_error [15:0] $end
$upscope $end
$upscope $end
$enddefinitions $end
$comment Show the parameter values. $end
$dumpall
b1000000000000 1
b100000000 0
b100000000000 /
$end
#0
$dumpvars
b0 :
b0 9
bx 8
bx 7
b0 6
bx 5
bx 4
bx 3
bx 2
b1100100 .
b0 -
b0 ,
bx +
bx *
bx )
bx (
bx '
bx &
b1100100 %
1$
b0 #
0"
b0 !
$end
#5
bx :
bx !
bx 6
b0 '
b0 3
bx ,
bx 9
b1100100 +
b1100100 8
1"
0$
#10
0"
#15
b1100100 :
bx '
bx 3
b1100100000000000000 )
b1100100000000000000 5
b110010 +
b110010 8
1"
b110010 #
b110010 -
#20
0"
#25
b110010 :
b1111111111001110 *
b1111111111001110 7
b110010000000000000 )
b110010000000000000 5
b11001 +
b11001 8
1"
b1001011 #
b1001011 -
#30
0"
#35
b11001 :
b11111111111111100111000000000000 &
b11111111111111100111000000000000 2
b1111111111100111 *
b1111111111100111 7
b11001000000000000 )
b11001000000000000 5
b0 +
b0 8
1"
b1100100 #
b1100100 -
#40
0"
#45
b0 :
b11111111111111110011100000000000 &
b11111111111111110011100000000000 2
b0 )
b0 5
b1111111111100111 +
b1111111111100111 8
1"
b1111101 #
b1111101 -
#50
0"
#55
b1111111111100111 :
b11111111111111100111000000000000 )
b11111111111111100111000000000000 5
b1111111111001110 +
b1111111111001110 8
1"
b10010110 #
b10010110 -
#60
0"
#65
b1111111111001110 :
b11111111111111001110000000000000 )
b11111111111111001110000000000000 5
1"
#70
0"
#75
b0 *
b0 7
1"
#80
0"
#85
b0 &
b0 2
1"
